odoo/addons/barcode_generator_product_variant/README.rst
odoo/addons/barcode_generator_product_variant/__init__.py
odoo/addons/barcode_generator_product_variant/__manifest__.py
odoo/addons/barcode_generator_product_variant/demo/barcode_rule_demo.xml
odoo/addons/barcode_generator_product_variant/i18n/barcode_generator_product_variant.pot
odoo/addons/barcode_generator_product_variant/models/__init__.py
odoo/addons/barcode_generator_product_variant/models/product_template.py
odoo/addons/barcode_generator_product_variant/readme/CONTRIBUTORS.rst
odoo/addons/barcode_generator_product_variant/readme/DESCRIPTION.rst
odoo/addons/barcode_generator_product_variant/readme/USAGE.rst
odoo/addons/barcode_generator_product_variant/security/ir.model.access.csv
odoo/addons/barcode_generator_product_variant/static/description/icon.png
odoo/addons/barcode_generator_product_variant/static/description/index.html
odoo/addons/barcode_generator_product_variant/tests/__init__.py
odoo/addons/barcode_generator_product_variant/tests/test_barcode_generator_product_variant.py
odoo/addons/barcode_generator_product_variant/views/product_template_views.xml
odoo/addons/barcode_generator_product_variant/wizards/__init__.py
odoo/addons/barcode_generator_product_variant/wizards/product_product_barcode_wizard.py
odoo/addons/barcode_generator_product_variant/wizards/product_product_barcode_wizard_views.xml
odoo14_addon_barcode_generator_product_variant-14.0.1.0.1.dist-info/METADATA
odoo14_addon_barcode_generator_product_variant-14.0.1.0.1.dist-info/WHEEL
odoo14_addon_barcode_generator_product_variant-14.0.1.0.1.dist-info/top_level.txt
odoo14_addon_barcode_generator_product_variant-14.0.1.0.1.dist-info/RECORD
